main.py
iflow_mcp_fastmcp_data_analysis_server-0.1.4.dist-info/METADATA
iflow_mcp_fastmcp_data_analysis_server-0.1.4.dist-info/WHEEL
iflow_mcp_fastmcp_data_analysis_server-0.1.4.dist-info/entry_points.txt
iflow_mcp_fastmcp_data_analysis_server-0.1.4.dist-info/top_level.txt
iflow_mcp_fastmcp_data_analysis_server-0.1.4.dist-info/RECORD
